app.py
view_my_photos-1.0.2.dist-info/METADATA
view_my_photos-1.0.2.dist-info/WHEEL
view_my_photos-1.0.2.dist-info/entry_points.txt
view_my_photos-1.0.2.dist-info/top_level.txt
view_my_photos-1.0.2.dist-info/RECORD
